xray_cfo/__init__.py
xray_cfo/__main__.py
xray_cfo/base.py
xray_cfo/cli.py
xray_cfo/message_pool.py
xray_cfo/api_services/__init__.py
xray_cfo/api_services/_base.py
xray_cfo/api_services/grpc/__init__.py
xray_cfo/api_services/handler/__init__.py
xray_cfo/api_services/handler/add_client.py
xray_cfo/api_services/handler/add_inbound.py
xray_cfo/api_services/handler/add_outbound.py
xray_cfo/api_services/handler/alter_inbound.py
xray_cfo/api_services/handler/alter_outbound.py
xray_cfo/api_services/handler/get_inbound_users.py
xray_cfo/api_services/handler/list_bound.py
xray_cfo/api_services/handler/remove_bound.py
xray_cfo/api_services/handler/remove_client.py
xray_cfo/api_services/logger/__init__.py
xray_cfo/api_services/observatory/__init__.py
xray_cfo/api_services/routing/__init__.py
xray_cfo/api_services/stats/__init__.py
xray_cfo/client/__init__.py
xray_cfo/client/async_client.py
xray_cfo/common/__init__.py
xray_cfo/common/utils.py
xray_cfo/exceptions/__init__.py
xray_cfo/exceptions/_base.py
xray_cfo/exceptions/email_already_exists.py
xray_cfo/exceptions/email_not_found.py
xray_cfo/exceptions/inbound_not_found.py
xray_cfo/models/__init__.py
xray_cfo/models/xray/__init__.py
xray_cfo/models/xray/_base.py
xray_cfo/models/xray/api.py
xray_cfo/models/xray/dns.py
xray_cfo/models/xray/enums.py
xray_cfo/models/xray/fake_dns.py
xray_cfo/models/xray/log.py
xray_cfo/models/xray/metrics.py
xray_cfo/models/xray/observatory.py
xray_cfo/models/xray/policy.py
xray_cfo/models/xray/reverse.py
xray_cfo/models/xray/routing.py
xray_cfo/models/xray/stats.py
xray_cfo/models/xray/inbound/__init__.py
xray_cfo/models/xray/inbound/dokodemo.py
xray_cfo/models/xray/inbound/http.py
xray_cfo/models/xray/inbound/shadowsocks.py
xray_cfo/models/xray/inbound/socks.py
xray_cfo/models/xray/inbound/trojan.py
xray_cfo/models/xray/inbound/vless.py
xray_cfo/models/xray/inbound/vmess.py
xray_cfo/models/xray/inbound/wireguard.py
xray_cfo/models/xray/outbound/__init__.py
xray_cfo-0.1.0.dist-info/METADATA
xray_cfo-0.1.0.dist-info/WHEEL
xray_cfo-0.1.0.dist-info/top_level.txt
xray_cfo-0.1.0.dist-info/RECORD
