Metadata-Version: 2.4
Name: xray-cfo
Version: 0.1.0
Summary: This is a library for xray-core created using autogeneration with the betterproto2 plugin
Author-email: CFOSUP <cfosup@proton.me>
License-Expression: MIT
Requires-Python: >=3.13
Requires-Dist: betterproto2[all]>=0.5.1
Requires-Dist: cryptography>=44.0.3
Requires-Dist: grpcio-tools>=1.71.0
Requires-Dist: pydantic>=2.11.4
